sometime/__init__.py
sometime/sometime.py
sometime-1.2.2.dist-info/WHEEL
sometime-1.2.2.dist-info/METADATA
sometime-1.2.2.dist-info/licenses/LICENSE
sometime-1.2.2.dist-info/RECORD
