Metadata-Version: 2.1
Name: sometime
Version: 1.2.2
Summary: Get timestamp, formatted date, and perform date/time operations.
License: LICENSE.txt
Keywords: date,time,timestamp,utc
Author: Rodney Maniego Jr.
Author-email: rodney.maniegojr@gmail.com
Requires-Python: >=3.10
Classifier: Development Status :: 5 - Production/Stable
Classifier: Intended Audience :: Developers
Classifier: License :: OSI Approved :: MIT License
Classifier: Programming Language :: Python :: 3
Classifier: Topic :: Software Development :: Build Tools
Project-URL: documentation, https://sometime.readthedocs.io
Project-URL: homepage, https://github.com/rmaniego/sometime
